{
  "artists": [
    {
      "id": "example-artist",
      "name": "Пример исполнителя",
      "songs": [
        {
          "id": "example-song",
          "title": "Пример песни",
          "key": "Am",
          "bpm": 90,
          "sourceUrl": "https://mytabs.ru/",
          "body": "[Am]Это пример строки текста песни\n[F]      [C]        [G]\n[Am]Аккорды пишутся в квадратных скобках прямо перед словом,\n[F]      [C]        [G]\nнад которым они звучат — так же, как на mytabs.ru."
        }
      ]
    }
  ]
}
